[
    {
        "actionName": "createTicket",
        "steps": [
            {
                "stepId": "STEP280",
                "stepName": "Url: welcome.pl",
                "infFile": "t3.inf",
                "time": 1618000349835
            },
            {
                "stepId": "STEP281",
                "stepName": "Submit Data: reservations.pl",
                "infFile": "t4.inf",
                "time": 1618000350198
            },
            {
                "stepId": "STEP282",
                "stepName": "Submit Data: reservations.pl",
                "infFile": "t5.inf",
                "time": 1618000350519
            },
            {
                "stepId": "STEP283",
                "stepName": "Submit Data: reservations.pl",
                "infFile": "t6.inf",
                "time": 1618000350843
            },
            {
                "stepId": "STEP284",
                "stepName": "Submit Data: reservations.pl",
                "infFile": "t7.inf",
                "time": 1618000351196
            },
            {
                "stepId": "STEP285",
                "stepName": "Submit Form: reservations.pl_2",
                "infFile": "t8.inf",
                "time": 1618000351541
            },
            {
                "stepId": "STEP286",
                "stepName": "Submit Form: reservations.pl_3",
                "infFile": "t9.inf",
                "time": 1618000351906
            }
        ],
        "transactions": []
    }
]